{
  "originalAlarm": {
    "alarmType": "NULLPTR_DEREFERENCE",
    "description": "`curr` could be null (null value originating from line 65) and is dereferenced.",
    "fileLocation": "/workspace/285//workspace/varbugs/2631486f1bf.c",
    "line": 66,
    "analysisTime": 1.095908081
  },
  "configFiles": [],
  "presenceCondition": "(and (= CONFIG_FEATURE_LS_RECURSIVE false)\n     (= CONFIG_FEATURE_LS_SORTFILES false))",
  "model": "(define-fun CONFIG_FEATURE_LS_RECURSIVE () Bool\n  false)\n(define-fun CONFIG_FEATURE_LS_SORTFILES () Bool\n  false)",
  "numConfigs": [
    2
  ],
  "strategy": "product",
  "classification": "TRUE_NEW_OVER",
  "old_id": null,
  "id": "PRODUCT_151",
  "reasoning": "Line 66: curr->val dereferenced after malloc at L65 without NULL check \u2014 null dereference in main() outside any #ifdef. Occurs in all configs. No '// ERROR' at L66 \u2192 new bug. PC (RECURSIVE=F AND SORTFILES=F) over-constrained. Classification: TRUE_NEW_OVER."
}